pyqt_left_right_text_completer/__init__.py
pyqt_left_right_text_completer/leftRightTextCompleter.py
pyqt_left_right_text_completer-0.0.1.dist-info/LICENSE
pyqt_left_right_text_completer-0.0.1.dist-info/METADATA
pyqt_left_right_text_completer-0.0.1.dist-info/WHEEL
pyqt_left_right_text_completer-0.0.1.dist-info/top_level.txt
pyqt_left_right_text_completer-0.0.1.dist-info/RECORD
