Metadata-Version: 2.1
Name: pyqt-left-right-text-completer
Version: 0.0.1
Summary: PyQt left text, right text completer. Left text is major target of search.
Home-page: https://github.com/yjg30737/pyqt-left-right-text-completer.git
Author: Jung Gyu Yoon
Author-email: yjg30737@gmail.com
License: MIT
Platform: UNKNOWN
License-File: LICENSE
Requires-Dist: PyQt5 (>=5.8)
